animalchess/__init__.py
animalchess/chess/__init__.py
animalchess/chess/board.py
animalchess/chess/pieces.py
animalchess/chess/player.py
animalchess/chess/utils.py
animalchess-0.0.1.dist-info/licenses/LICENSE
animalchess-0.0.1.dist-info/METADATA
animalchess-0.0.1.dist-info/WHEEL
animalchess-0.0.1.dist-info/top_level.txt
animalchess-0.0.1.dist-info/RECORD
