Metadata-Version: 2.4
Name: animalchess
Version: 0.0.1
Summary: Chinese Animal Chess
Author-email: Kwan Yuet Stephen Ho <stephenhky@yahoo.com.hk>
License: MIT
Project-URL: Repository, https://github.com/stephenhky/ChineseAnimalChess
Project-URL: Issues, https://github.com/stephenhky/ChineseAnimalChess/issues
Keywords: animal chess,pygame
Classifier: Topic :: Scientific/Engineering :: Mathematics
Classifier: License :: OSI Approved :: MIT License
Classifier: Topic :: Software Development :: Libraries :: Python Modules
Classifier: Topic :: Software Development :: Version Control :: Git
Classifier: Programming Language :: Python :: 3.11
Classifier: Programming Language :: Python :: 3.12
Classifier: Programming Language :: Python :: 3.13
Classifier: Intended Audience :: Developers
Requires-Python: >=3.11
License-File: LICENSE
Requires-Dist: numpy
Requires-Dist: loguru
Provides-Extra: test
Requires-Dist: pytest; extra == "test"
Dynamic: license-file
